{
  "name": "NotesAides Workspace",
  "image": "mcr.microsoft.com/devcontainers/base:ubuntu",
  "features": {
    "ghcr.io/devcontainers/features/node:1": {
      "version": "lts",
      "pnpm": "latest"
    },
    "ghcr.io/devcontainers-contrib/features/bun:1": {
      "version": "latest"
    },
    "ghcr.io/devcontainers/features/rust:1": {
      "version": "latest",
      "profile": "default"
    },
    "ghcr.io/devcontainers/features/docker-in-docker:2": {
      "version": "latest",
      "enableNonRootDocker": "true",
      "moby": "true"
    }
  },
  "customizations": {
    "vscode": {
      "settings": {
        "terminal.integrated.defaultProfile.linux": "bash"
      },
      "extensions": [
        "dbaeumer.vscode-eslint",
        "esbenp.prettier-vscode",
        "rust-lang.rust-analyzer",
        "oven.bun-vscode",
        "bradlc.vscode-tailwindcss",
        "ms-azuretools.vscode-docker"
      ]
    }
  },
  "forwardPorts": [3000, 3001, 5432],
  "portsAttributes": {
    "3000": {
      "label": "Next.js Frontend",
      "onAutoForward": "notify"
    },
    "3001": {
      "label": "Hono API",
      "onAutoForward": "notify"
    },
    "5432": {
      "label": "PostgreSQL Database",
      "onAutoForward": "silent"
    }
  },
  "postCreateCommand": "pnpm install"
}
